rtl/adder4b_sample.v
// 4-bit Ripple Carry Adder
// This module implements a 4-bit adder using full adders in a ripple-carry configuration

module adder_4bit (
    input [3:0] a,      // First 4-bit input
    input [3:0] b,      // Second 4-bit input
    input cin,          // Carry input
    output [3:0] sum,   // 4-bit sum output
    output cout         // Carry output
);

    // Internal carry signals
    wire c1, c2, c3;
    
    // Instantiate 4 full adders
    full_adder fa0 (.a(a[0]), .b(b[0]), .cin(cin), .sum(sum[0]), .cout(c1));
    full_adder fa1 (.a(a[1]), .b(b[1]), .cin(c1),  .sum(sum[1]), .cout(c2));
    full_adder fa2 (.a(a[2]), .b(b[2]), .cin(c2),  .sum(sum[2]), .cout(c3));
    full_adder fa3 (.a(a[3]), .b(b[3]), .cin(c3),  .sum(sum[3]), .cout(cout));

endmodule

// Full Adder module
module full_adder (
    input a,        // First input bit
    input b,        // Second input bit
    input cin,      // Carry input
    output sum,     // Sum output
    output cout     // Carry output
);

    // Sum = a XOR b XOR cin
    assign sum = a ^ b ^ cin;
    
    // Carry out = (a AND b) OR (cin AND (a XOR b))
    assign cout = (a & b) | (cin & (a ^ b));

endmodule

rtl/adder4b_tb_sample.v
// Testbench for 4-bit Ripple Carry Adder
// This testbench tests various scenarios including edge cases

`timescale 1ns/1ps

module adder4b_tb;

    // Testbench signals
    reg [3:0] a, b;     // Input operands
    reg cin;            // Carry input
    wire [3:0] sum;     // Sum output
    wire cout;          // Carry output
    
    // Expected results for verification
    reg [4:0] expected_result;  // 5-bit to hold carry + 4-bit sum
    reg [4:0] actual_result;    // 5-bit to hold carry + 4-bit sum
    
    // Instantiate the Device Under Test (DUT)
    adder_4bit dut (
        .a(a),
        .b(b),
        .cin(cin),
        .sum(sum),
        .cout(cout)
    );
    
    // Test stimulus and verification
    initial begin
        $display("Starting 4-bit Adder Testbench");
        $display("Time\tA\tB\tCin\tSum\tCout\tExpected\tStatus");
        $display("----------------------------------------------------------------");
        
        // Test Case 1: Basic addition without carry
        a = 4'b0000; b = 4'b0000; cin = 1'b0;
        #10;
        expected_result = 5'b00000;  // 0 + 0 + 0 = 0
        actual_result = {cout, sum};
        check_result("Basic 0+0");
        
        // Test Case 2: Simple addition
        a = 4'b0001; b = 4'b0001; cin = 1'b0;
        #10;
        expected_result = 5'b00010;  // 1 + 1 + 0 = 2
        actual_result = {cout, sum};
        check_result("Simple 1+1");
        
        // Test Case 3: Addition with carry input
        a = 4'b0001; b = 4'b0001; cin = 1'b1;
        #10;
        expected_result = 5'b00011;  // 1 + 1 + 1 = 3
        actual_result = {cout, sum};
        check_result("With carry 1+1+1");
        
        // Test Case 4: Maximum values without overflow
        a = 4'b0111; b = 4'b0001; cin = 1'b0;
        #10;
        expected_result = 5'b01000;  // 7 + 1 + 0 = 8
        actual_result = {cout, sum};
        check_result("Max-1 + 1");
        
        // Test Case 5: Overflow case
        a = 4'b1111; b = 4'b0001; cin = 1'b0;
        #10;
        expected_result = 5'b10000;  // 15 + 1 + 0 = 16 (overflow)
        actual_result = {cout, sum};
        check_result("Overflow 15+1");
        
        // Test Case 6: Maximum overflow
        a = 4'b1111; b = 4'b1111; cin = 1'b1;
        #10;
        expected_result = 5'b11111;  // 15 + 15 + 1 = 31
        actual_result = {cout, sum};
        check_result("Max overflow 15+15+1");
        
        // Test Case 7: Random test cases
        a = 4'b1010; b = 4'b0101; cin = 1'b0;  // 10 + 5 = 15
        #10;
        expected_result = 5'b01111;
        actual_result = {cout, sum};
        check_result("Random 10+5");
        
        a = 4'b1100; b = 4'b0011; cin = 1'b1;  // 12 + 3 + 1 = 16
        #10;
        expected_result = 5'b10000;
        actual_result = {cout, sum};
        check_result("Random 12+3+1");
        
        // Test Case 8: Edge cases with different bit patterns
        a = 4'b1010; b = 4'b0101; cin = 1'b0;  // 10 + 5 = 15
        #10;
        expected_result = 5'b01111;
        actual_result = {cout, sum};
        check_result("Pattern 1010+0101");
        
        a = 4'b1111; b = 4'b0000; cin = 1'b1;  // 15 + 0 + 1 = 16
        #10;
        expected_result = 5'b10000;
        actual_result = {cout, sum};
        check_result("Pattern 1111+0000+1");
        
        $display("----------------------------------------------------------------");
        $display("Testbench completed!");
        $finish;
    end
    
    // Task to check and display results
    task check_result;
        input [80:0] test_name;
        begin
            $write("%0t\t%h\t%h\t%b\t%h\t%b\t%b\t", 
                   $time, a, b, cin, sum, cout, expected_result);
            
            if (actual_result == expected_result) begin
                $display("PASS");
            end else begin
                $display("FAIL - Expected: %b, Got: %b", expected_result, actual_result);
            end
        end
    endtask
    
    // Generate VCD file for waveform viewing
    initial begin
        $dumpfile("adder4b_tb.vcd");
        $dumpvars(0, adder4b_tb);
    end

endmodule

rtl/adder4b_tb.vcd
$date
	Mon Sep  8 21:42:10 2025
$end
$version
	Icarus Verilog
$end
$timescale
	1ps
$end
$scope module adder4b_tb $end
$var wire 4 ! sum [3:0] $end
$var wire 1 " cout $end
$var reg 4 # a [3:0] $end
$var reg 5 $ actual_result [4:0] $end
$var reg 4 % b [3:0] $end
$var reg 1 & cin $end
$var reg 5 ' expected_result [4:0] $end
$scope module dut $end
$var wire 4 ( a [3:0] $end
$var wire 4 ) b [3:0] $end
$var wire 1 & cin $end
$var wire 4 * sum [3:0] $end
$var wire 1 " cout $end
$var wire 1 + c3 $end
$var wire 1 , c2 $end
$var wire 1 - c1 $end
$scope module fa0 $end
$var wire 1 . a $end
$var wire 1 / b $end
$var wire 1 & cin $end
$var wire 1 - cout $end
$var wire 1 0 sum $end
$upscope $end
$scope module fa1 $end
$var wire 1 1 a $end
$var wire 1 2 b $end
$var wire 1 - cin $end
$var wire 1 , cout $end
$var wire 1 3 sum $end
$upscope $end
$scope module fa2 $end
$var wire 1 4 a $end
$var wire 1 5 b $end
$var wire 1 , cin $end
$var wire 1 + cout $end
$var wire 1 6 sum $end
$upscope $end
$scope module fa3 $end
$var wire 1 7 a $end
$var wire 1 8 b $end
$var wire 1 + cin $end
$var wire 1 " cout $end
$var wire 1 9 sum $end
$upscope $end
$upscope $end
$scope task check_result $end
$var reg 81 : test_name [80:0] $end
$upscope $end
$upscope $end
$enddefinitions $end
#0
$dumpvars
bx :
09
08
07
06
05
04
03
02
01
00
0/
0.
0-
0,
0+
b0 *
b0 )
b0 (
bx '
0&
b0 %
bx $
b0 #
0"
b0 !
$end
#10000
b10 !
b10 *
13
1-
1/
1.
b1 %
b1 )
b1 #
b1 (
b10000100110000101110011011010010110001100100000001100000010101100110000 :
b0 $
b0 '
#20000
b11 !
b11 *
10
1&
b1010011011010010110110101110000011011000110010100100000001100010010101100110001 :
b10 $
b10 '
#30000
19
1+
1,
03
06
b1000 !
b1000 *
00
11
14
0&
b111 #
b111 (
b101100001011100100111001001111001001000000011000100101011001100010010101100110001 :
b11 $
b11 '
#40000
1"
b0 !
b0 *
09
17
b1111 #
b1111 (
b10011010110000101111000001011010011000100100000001010110010000000110001 :
b1000 $
b1000 '
#50000
13
16
19
b1111 !
b1111 *
10
12
15
18
1&
b1111 %
b1111 )
b101110010011001100110110001101111011101110010000000110001001101010010101100110001 :
b10000 $
b10000 '
#60000
0"
0+
0,
19
0-
16
b1111 !
b1111 *
10
02
08
0.
04
0&
b101 %
b101 )
b1010 #
b1010 (
b1101111011101110010000000110001001101010010101100110001001101010010101100110001 :
b11111 $
b11111 '
#70000
1"
09
1+
06
1,
03
1-
b0 !
b0 *
00
12
05
01
14
1&
b11 %
b11 )
b1100 #
b1100 (
b1100001011011100110010001101111011011010010000000110001001100000010101100110101 :
b1111 $
b1111 '
#80000
0"
19
0+
16
0,
13
0-
b1111 !
b1111 *
10
02
15
11
04
0&
b101 %
b101 )
b1010 #
b1010 (
b1100100011011110110110100100000001100010011001000101011001100110010101100110001 :
b10000 $
b10000 '
#90000
1"
09
1+
06
1,
03
1-
b0 !
b0 *
00
0/
05
1.
14
1&
b0 %
b0 )
b1111 #
b1111 (
b100000001100010011000000110001001100000010101100110000001100010011000000110001 :
b1111 $
b1111 '
#100000
b100110001001100010011000100101011001100000011000000110000001100000010101100110001 :
b10000 $
b10000 '
